[
  {
    "region_code": "11110",
    "region_name": "서울특별시 종로구 청운효자동",
    "lat": 37.5760,
    "lon": 126.9669,
    "species": "cherry",
    "predicted_date": "2025-04-08",
    "confidence_low": "2025-04-05",
    "confidence_high": "2025-04-12",
    "model_version": "v0.9.3",
    "updated_at": "2025-01-14T09:00:00+09:00"
  },
  {
    "region_code": "11110",
    "region_name": "서울특별시 종로구 청운효자동",
    "lat": 37.5760,
    "lon": 126.9669,
    "species": "forsythia",
    "predicted_date": "2025-03-25",
    "confidence_low": "2025-03-22",
    "confidence_high": "2025-03-28",
    "model_version": "v0.9.3",
    "updated_at": "2025-01-14T09:00:00+09:00"
  },
  {
    "region_code": "11110",
    "region_name": "서울특별시 종로구 청운효자동",
    "lat": 37.5760,
    "lon": 126.9669,
    "species": "azalea",
    "predicted_date": "2025-04-15",
    "confidence_low": "2025-04-12",
    "confidence_high": "2025-04-18",
    "model_version": "v0.9.3",
    "updated_at": "2025-01-14T09:00:00+09:00"
  },
  {
    "region_code": "26110",
    "region_name": "부산광역시 중구 중앙동",
    "lat": 35.1040,
    "lon": 129.0340,
    "species": "cherry",
    "predicted_date": "2025-03-28",
    "confidence_low": "2025-03-25",
    "confidence_high": "2025-04-01",
    "model_version": "v0.9.3",
    "updated_at": "2025-01-14T09:00:00+09:00"
  },
  {
    "region_code": "26110",
    "region_name": "부산광역시 중구 중앙동",
    "lat": 35.1040,
    "lon": 129.0340,
    "species": "forsythia",
    "predicted_date": "2025-03-18",
    "confidence_low": "2025-03-15",
    "confidence_high": "2025-03-21",
    "model_version": "v0.9.3",
    "updated_at": "2025-01-14T09:00:00+09:00"
  },
  {
    "region_code": "26110",
    "region_name": "부산광역시 중구 중앙동",
    "lat": 35.1040,
    "lon": 129.0340,
    "species": "azalea",
    "predicted_date": "2025-04-05",
    "confidence_low": "2025-04-02",
    "confidence_high": "2025-04-08",
    "model_version": "v0.9.3",
    "updated_at": "2025-01-14T09:00:00+09:00"
  },
  {
    "region_code": "27110",
    "region_name": "대구광역시 중구 삼덕동",
    "lat": 35.8722,
    "lon": 128.5963,
    "species": "cherry",
    "predicted_date": "2025-04-02",
    "confidence_low": "2025-03-30",
    "confidence_high": "2025-04-05",
    "model_version": "v0.9.3",
    "updated_at": "2025-01-14T09:00:00+09:00"
  },
  {
    "region_code": "27110",
    "region_name": "대구광역시 중구 삼덕동",
    "lat": 35.8722,
    "lon": 128.5963,
    "species": "forsythia",
    "predicted_date": "2025-03-20",
    "confidence_low": "2025-03-17",
    "confidence_high": "2025-03-23",
    "model_version": "v0.9.3",
    "updated_at": "2025-01-14T09:00:00+09:00"
  },
  {
    "region_code": "27110",
    "region_name": "대구광역시 중구 삼덕동",
    "lat": 35.8722,
    "lon": 128.5963,
    "species": "azalea",
    "predicted_date": "2025-04-10",
    "confidence_low": "2025-04-07",
    "confidence_high": "2025-04-13",
    "model_version": "v0.9.3",
    "updated_at": "2025-01-14T09:00:00+09:00"
  },
  {
    "region_code": "41111",
    "region_name": "경기도 수원시 영통구 매탄동",
    "lat": 37.2636,
    "lon": 127.0286,
    "species": "cherry",
    "predicted_date": "2025-04-10",
    "confidence_low": "2025-04-07",
    "confidence_high": "2025-04-13",
    "model_version": "v0.9.3",
    "updated_at": "2025-01-14T09:00:00+09:00"
  },
  {
    "region_code": "41111",
    "region_name": "경기도 수원시 영통구 매탄동",
    "lat": 37.2636,
    "lon": 127.0286,
    "species": "forsythia",
    "predicted_date": "2025-03-27",
    "confidence_low": "2025-03-24",
    "confidence_high": "2025-03-30",
    "model_version": "v0.9.3",
    "updated_at": "2025-01-14T09:00:00+09:00"
  },
  {
    "region_code": "41111",
    "region_name": "경기도 수원시 영통구 매탄동",
    "lat": 37.2636,
    "lon": 127.0286,
    "species": "azalea",
    "predicted_date": "2025-04-17",
    "confidence_low": "2025-04-14",
    "confidence_high": "2025-04-20",
    "model_version": "v0.9.3",
    "updated_at": "2025-01-14T09:00:00+09:00"
  }
]